firehose_sipper/__init__.py
firehose_sipper-0.4.0.dist-info/WHEEL
firehose_sipper-0.4.0.dist-info/METADATA
firehose_sipper-0.4.0.dist-info/RECORD
