Metadata-Version: 2.1
Name: firehose-sipper
Version: 0.4.0
Summary: Parses firehosed json from S3
License: MIT
Author: Bob Gregory
Author-email: bob@codefiend.co.uk
Requires-Python: >=3.10,<4.0
Classifier: License :: OSI Approved :: MIT License
Classifier: Programming Language :: Python :: 3
Classifier: Programming Language :: Python :: 3.10
Requires-Dist: boto3 (>=1.20.54,<2.0.0)
